{
    "items": {
        "Adventurous": 0,
        "Appreciative (Grateful)": 1,
        "Articulate (Well-spoken, Expressive)": 2,
        "Attractive": 3,
        "Brilliant": 4,
        "Calm": 5,
        "Captivating": 6,
        "Caring": 7,
        "Charming": 8,
        "Cheerful": 9,
        "Clever": 10,
        "Colorful (Full of Life, Interesting)": 11,
        "Compassionate (Sympathetic, Warm)": 12,
        "Confident": 13,
        "Considerate": 14,
        "Contemplative (Reflective, Thoughtful)": 15,
        "Courageous": 16,
        "Creative": 17,
        "Cultured (Refined, Educated)": 18,
        "Curious": 19,
        "Daring": 20,
        "Deep": 21,
        "Dramatic": 22,
        "Earnest (Enthusiastic)": 23,
        "Elegant": 24,
        "Eloquent (Well-spoken, Expressive)": 25,
        "Empathetic": 26,
        "Energetic": 27,
        "Enthusiastic": 28,
        "Exciting": 29,
        "Extraordinary": 30,
        "Freethinking": 31,
        "Fun-loving": 32,
        "Gentle": 33,
        "Happy": 34,
        "Honest": 35,
        "Humble": 36,
        "Humorous": 37,
        "Idealistic": 38,
        "Imaginative": 39,
        "Insightful": 40,
        "Intelligent": 41,
        "Kind": 42,
        "Knowledgeable": 43,
        "Logical": 44,
        "Meticulous (Precise, Thorough)": 45,
        "Objective (Detached, Impartial)": 46,
        "Observant": 47,
        "Open": 48,
        "Optimistic": 49,
        "Passionate": 50,
        "Patriotic": 51,
        "Peaceful": 52,
        "Perceptive": 53,
        "Playful": 54,
        "Practical": 55,
        "Profound": 56,
        "Rational": 57,
        "Realistic": 58,
        "Reflective": 59,
        "Relaxed": 60,
        "Respectful": 61,
        "Romantic": 62,
        "Rustic (Rural)": 63,
        "Scholarly": 64,
        "Sensitive": 65,
        "Sentimental": 66,
        "Serious": 67,
        "Simple": 68,
        "Sophisticated": 69,
        "Spirited": 70,
        "Spontaneous": 71,
        "Stoic (Unemotional, Matter-of-fact)": 72,
        "Suave (Charming, Smooth)": 73,
        "Sweet": 74,
        "Sympathetic": 75,
        "Vivacious (Lively, Animated)": 76,
        "Warm": 77,
        "Wise": 78,
        "Witty": 79,
        "Youthful": 80,
        "Absentminded": 81,
        "Aggressive": 82,
        "Amusing": 83,
        "Artful": 84,
        "Boyish": 85,
        "Breezy (Relaxed, Informal)": 86,
        "Businesslike": 87,
        "Casual": 88,
        "Cerebral (Intellectual, Logical)": 89,
        "Complex": 90,
        "Conservative (Traditional, Conventional)": 91,
        "Contradictory": 92,
        "Cute": 93,
        "Dreamy": 94,
        "Dry": 95,
        "Emotional": 96,
        "Enigmatic (Cryptic, Obscure)": 97,
        "Formal": 98,
        "Glamorous": 99,
        "High-spirited": 100,
        "Impersonal": 101,
        "Intense": 102,
        "Maternal (Mother-like)": 103,
        "Mellow (Soothing, Sweet)": 104,
        "Mystical": 105,
        "Neutral": 106,
        "Old-fashioned": 107,
        "Ordinary": 108,
        "Questioning": 109,
        "Sarcastic": 110,
        "Sensual": 111,
        "Skeptical": 112,
        "Solemn": 113,
        "Stylish": 114,
        "Tough": 115,
        "Whimsical (Playful, Fanciful)": 116,
        "Abrasive (Annoying, Irritating)": 117,
        "Airy (Casual, Not Serious)": 118,
        "Aloof (Detached, Distant)": 119,
        "Angry": 120,
        "Anxious": 121,
        "Apathetic (Uncaring, Disinterested)": 122,
        "Argumentative": 123,
        "Arrogant": 124,
        "Artificial": 125,
        "Assertive": 126,
        "Barbaric": 127,
        "Bewildered (Astonished, Confused)": 128,
        "Bizarre": 129,
        "Bland": 130,
        "Blunt": 131,
        "Boisterous (Rowdy, Loud)": 132,
        "Childish": 133,
        "Coarse (Not Fine, Crass)": 134,
        "Cold": 135,
        "Conceited (Arrogant, Egotistical)": 136,
        "Confused": 137,
        "Contemptible (Despicable, Vile)": 138,
        "Cowardly": 139,
        "Crazy": 140,
        "Critical": 141,
        "Cruel": 142,
        "Cynical (Doubtful, Skeptical)": 143,
        "Destructive": 144,
        "Devious": 145,
        "Discouraging": 146,
        "Disturbing": 147,
        "Dull": 148,
        "Egocentric (Self-centered)": 149,
        "Envious": 150,
        "Erratic": 151,
        "Escapist (Dreamer, Seeks Distraction)": 152,
        "Excitable": 153,
        "Extravagant": 154,
        "Extreme": 155,
        "Fanatical": 156,
        "Fanciful": 157,
        "Fatalistic (Bleak, Gloomy)": 158,
        "Fawning (Flattering, Deferential)": 159,
        "Fearful": 160,
        "Fickle (Changeable, Temperamental)": 161,
        "Fiery": 162,
        "Foolish": 163,
        "Frightening": 164,
        "Frivolous (Trivial, Silly)": 165,
        "Gloomy": 166,
        "Grand": 167,
        "Grim": 168,
        "Hateful": 169,
        "Haughty (Arrogant, Snobbish)": 170,
        "Hostile": 171,
        "Irrational": 172,
        "Irritable": 173,
        "Lazy": 174,
        "Malicious": 175,
        "Melancholic": 176,
        "Miserable": 177,
        "Money-minded": 178,
        "Monstrous": 179,
        "Moody": 180,
        "Morbid": 181,
        "Narcissistic (Self-centered, Egotistical)": 182,
        "Neurotic (Manic, Obsessive)": 183,
        "Nihilistic": 184,
        "Obnoxious": 185,
        "Obsessive": 186,
        "Odd": 187,
        "Offhand": 188,
        "Opinionated": 189,
        "Outrageous": 190,
        "Overimaginative": 191,
        "Paranoid": 192,
        "Passive": 193,
        "Pompous (Self-important, Arrogant)": 194,
        "Pretentious (Snobbish, Showy)": 195,
        "Provocative": 196,
        "Quirky": 197,
        "Resentful": 198,
        "Ridiculous": 199,
        "Rigid": 200,
        "Rowdy": 201,
        "Scornful": 202,
        "Shy": 203,
        "Silly": 204,
        "Stiff": 205,
        "Stupid": 206,
        "Tense": 207,
        "Uncreative": 208,
        "Unimaginative": 209,
        "Unrealistic": 210,
        "Vacuous (Empty, Unintelligent)": 211,
        "Vague": 212,
        "Wishful": 213,
        "Zany": 214,
        "<Unknown>":215
    }
}